LICENSE
MANIFEST.in
README.md
pyproject.toml
setup.py
igibson/.gitignore
igibson/__init__.py
igibson/global_config.yaml
igibson/simulator.py
igibson/simulator_vr.py
igibson/vr_config.yaml
igibson.egg-info/PKG-INFO
igibson.egg-info/SOURCES.txt
igibson.egg-info/dependency_links.txt
igibson.egg-info/not-zip-safe
igibson.egg-info/requires.txt
igibson.egg-info/top_level.txt
igibson/action_primitives/__init__.py
igibson/action_primitives/action_primitive_set_base.py
igibson/action_primitives/starter_semantic_action_primitives.py
igibson/configs/behavior_robot_mp_behavior_task.yaml
igibson/configs/behavior_robot_vr_behavior_task.yaml
igibson/configs/fetch_motion_planning.yaml
igibson/configs/fetch_reaching.yaml
igibson/configs/fetch_rearrangement.yaml
igibson/configs/jr2_reaching.yaml
igibson/configs/locobot_nav.yaml
igibson/configs/tiago_nav.yaml
igibson/configs/turtlebot_dynamic_nav.yaml
igibson/configs/turtlebot_interactive_nav.yaml
igibson/configs/turtlebot_nav.yaml
igibson/configs/turtlebot_stadium_nav.yaml
igibson/configs/turtlebot_static_nav.yaml
igibson/configs/controllers/dd.yaml
igibson/configs/controllers/ik.yaml
igibson/configs/controllers/joint.yaml
igibson/configs/controllers/multi_finger_gripper.yaml
igibson/configs/controllers/null_gripper.yaml
igibson/configs/robots/ant.yaml
igibson/configs/robots/behavior_robot.yaml
igibson/configs/robots/fetch.yaml
igibson/configs/robots/freight.yaml
igibson/configs/robots/husky.yaml
igibson/configs/robots/jr2.yaml
igibson/configs/robots/locobot.yaml
igibson/configs/robots/tiago.yaml
igibson/configs/robots/turtlebot.yaml
igibson/controllers/__init__.py
igibson/controllers/controller_base.py
igibson/controllers/dd_controller.py
igibson/controllers/ik_controller.py
igibson/controllers/joint_controller.py
igibson/controllers/multi_finger_gripper_controller.py
igibson/controllers/null_gripper_controller.py
igibson/envs/__init__.py
igibson/envs/action_primitive_env.py
igibson/envs/env_base.py
igibson/envs/igibson_env.py
igibson/envs/igibson_ray_env.py
igibson/envs/parallel_env.py
igibson/examples/README.md
igibson/examples/__init__.py
igibson/examples/example_selector.py
