Metadata-Version: 2.1
Name: igibson
Version: 2.2.0
Summary: UNKNOWN
Home-page: https://github.com/StanfordVL/iGibson
Author: Stanford University
License: UNKNOWN
Platform: UNKNOWN
License-File: LICENSE
